rick/__init__.py
rick/version.py
rick/base/__init__.py
rick/base/container.py
rick/base/di.py
rick/base/maploader.py
rick/base/registry.py
rick/crypto/__init__.py
rick/crypto/fernet256.py
rick/crypto/hasher/__init__.py
rick/crypto/hasher/bcrypt.py
rick/crypto/hasher/hasher.py
rick/event/__init__.py
rick/event/handler.py
rick/event/manager.py
rick/filter/__init__.py
rick/filter/filter.py
rick/form/__init__.py
rick/form/field.py
rick/form/fieldrecord.py
rick/form/form.py
rick/mixin/__init__.py
rick/mixin/injectable.py
rick/mixin/translator.py
rick/request/__init__.py
rick/request/request.py
rick/request/requestrecord.py
rick/resource/__init__.py
rick/resource/cache.py
rick/resource/config/__init__.py
rick/resource/config/environment.py
rick/resource/config/json.py
rick/resource/redis/__init__.py
rick/resource/redis/redis.py
rick/serializer/__init__.py
rick/serializer/json/__init__.py
rick/serializer/json/json.py
rick/util/__init__.py
rick/util/cast.py
rick/util/loader.py
rick/validator/__init__.py
rick/validator/validator.py
rick/validator/rules/__init__.py
rick/validator/rules/hash.py
rick/validator/rules/misc.py
rick/validator/rules/net.py
rick/validator/rules/numeric.py
rick/validator/rules/rule.py
rick/validator/rules/strings.py
tests/__init__.py
tests/base/__init__.py
tests/base/test_container.py
tests/base/test_di.py
tests/base/test_registry.py
tests/crypto/__init__.py
tests/crypto/hasher/__init__.py
tests/crypto/hasher/test_bcrypt.py
tests/event/__init__.py
tests/event/test_manager.py
tests/filter/__init__.py
tests/filter/test_filter.py
tests/form/__init__.py
tests/form/test_field.py
tests/form/test_fieldrecord.py
tests/form/test_form.py
tests/request/__init__.py
tests/request/test_requestrecord.py
tests/request/test_requestrecord_setof.py
tests/resource/__init__.py
tests/resource/test_config_environment.py
tests/util/__init__.py
tests/util/test_loader.py
tests/validator/__init__.py
tests/validator/test_validator.py
tests/validator/test_validator_list.py
rick-0.3.1.dist-info/LICENSE
rick-0.3.1.dist-info/METADATA
rick-0.3.1.dist-info/WHEEL
rick-0.3.1.dist-info/top_level.txt
rick-0.3.1.dist-info/RECORD
